pyjoey/__init__.py
pyjoey/gui.py
pyjoey/interval_nfa_cep.py
pyjoey/interval_nfa_cep_c.py
pyjoey/interval_vector_cep.py
pyjoey/interval_vector_cep_c.py
pyjoey/nfa_cep.py
pyjoey/utils.py
pyjoey-0.2.4.dist-info/LICENSE
pyjoey-0.2.4.dist-info/METADATA
pyjoey-0.2.4.dist-info/WHEEL
pyjoey-0.2.4.dist-info/top_level.txt
pyjoey-0.2.4.dist-info/RECORD
