Metadata-Version: 2.1
Name: pyjoey
Version: 0.2.4
Summary: Event analytics. Very fast. Will eventually be merged into Quokka
Author: Tony Wang
Author-email: Tony Wang <zihengw@stanford.edu>
Classifier: Programming Language :: Python :: 3
Classifier: License :: OSI Approved :: MIT License
Classifier: Operating System :: OS Independent
Requires-Python: >=3.8
License-File: LICENSE
Requires-Dist: duckdb
Requires-Dist: pyarrow (>=7.0.0)
Requires-Dist: sqlglot (>=17.8.0)
Requires-Dist: tqdm (>=4.65.0)
Requires-Dist: polars (>=0.18.0)
